{"graphVersion":3,"nodes":[{"did":"did:plc:mlp2jdj6br2hxqlqk6sa4hj6","communities":["f119","s810","c4188","g928","e198","o10082"]},{"did":"did:plc:mlp2l6jn2biap2qvizfwfmme","communities":["f5866","s1516","c2718","g632","e4413","o7661"]},{"did":"did:plc:mlp3a27qdgkaffpw5fjzpcf7","communities":["f19","s284","c42208","g6306","e1463353","o484504"]},{"did":"did:plc:mlp4c2gmwjwrihadu6kxweex","communities":["f248","s203","c419","g369","e1960099","o6233"]},{"did":"did:plc:mlp5appboiltfgcwicoaz7x7","communities":["f218","s119","c562","g1120","e165675","o2953912"]},{"did":"did:plc:mlp5mvavvsobhobmtf2sniet","communities":["f81","s51","c48","g13579","e454344","o2172361"]},{"did":"did:plc:mlp6cjsyg4g42e5ifdsmxblm","communities":["f285","s386","c13212","g12906","e364","o2399784"]},{"did":"did:plc:mlp6dyg6xsgq7l6sd2zdqf6s","communities":["f119","s810","c4188","g928","e198","o10082"]},{"did":"did:plc:mlp6pgazzzlp5gvvjm5imffz","communities":["f395","s225","c45","g9759","e4808","o7356"]},{"did":"did:plc:mlp6ugq2rt6en25sadldvb2w","communities":["f2671","s291","c9632","g25778","e303721","o1355059"]},{"did":"did:plc:mlp77weavwzx2chyx3kqp32n","communities":["f21","s177","c84991","g12568","e2820600","o417007"]},{"did":"did:plc:mlp7vistlqggwdncsvflbjqp","communities":["f22","s284","c442","g1646","e37271","o273638"]},{"did":"did:plc:mlpcu3o7jrp65biz2ayumucq","communities":["f133","s444","c171","g10639","e167851","o2475772"]},{"did":"did:plc:mlpdiol5llgmdhtjr2thf5ub","communities":["f187","s1850","c941","g1938","e148433","o126298"]},{"did":"did:plc:mlpdiylpxj5llicaryzmb2t7","communities":["f19","s18","c85","g1054710","e2185020","o421340"]},{"did":"did:plc:mlpdmvieuru2ra2h6g7vqmwe","communities":["f70","s977","c13362","g7677","e3104914","o1815047"]},{"did":"did:plc:mlpfx65w4tbjdxjfsxhcravd","communities":["f3491","s799","c1779","g201","e1254266","o3224076"]},{"did":"did:plc:mlphj74ble2xqcbl5qgati47","communities":["f19","s7103","c2370","g10662","e65379","o255300"]},{"did":"did:plc:mlphqkuhlrkr4odrrhtanepy","communities":["f21","s177","c23182","g35788","e16919","o83856"]},{"did":"did:plc:mlpjzvwgmuf7dlyc43mvvioj","communities":["f1017","s36199","c9324","g24572","e30989","o15414"]},{"did":"did:plc:mlpk5z7h5bad5ejwcqih4o25","communities":["f13","s793","c16","g117","e45792","o45576"]},{"did":"did:plc:mlpkkezmmdctqotweuujvnlp","communities":["f2671","s622","c61","g686048","e73900","o2003579"]},{"did":"did:plc:mlplacou75b5h2fvzjr67dnr","communities":["f218","s119","c8","g435","e4948","o149310"]},{"did":"did:plc:mlpmfe7o53oyjlcedggac6tt","communities":["f395","s225","c254","g1054","e9608","o225097"]},{"did":"did:plc:mlpmhifwf46c2muar6ohaapc","communities":["f53","s8934","c2755","g386030","e3064206","o59505"]},{"did":"did:plc:mlpny5qm426kb3ynxklqygqw","communities":["f2406","s5792","c1983","g176165","e51454","o116493"]},{"did":"did:plc:mlpo4f2cn5i6fbdqtm2hfm72","communities":["f53","s29","c1056","g28368","e1450561","o580664"]},{"did":"did:plc:mlpoxki3wjtcfugsg4wszvfc","communities":["f3921","s3533","c10","g421","e134047","o2464021"]},{"did":"did:plc:mlpp42p32rv4r3ebfcbaobhe","communities":["f19","s677","c286","g10662","e2082461","o1507266"]},{"did":"did:plc:mlpp6q5tupf3ckydsfy2nsnl","communities":["f21","s4698","c2731","g3266621","e2572777","o1253440"]},{"did":"did:plc:mlppdu5usmdilpq225fd3yrt","communities":["f70","s802","c277","g104","e112417","o907810"]},{"did":"did:plc:mlppl6mpoc2jpn7vl6wcnpbu","communities":["f737","s652","c215","g509","e2078","o1346653"]},{"did":"did:plc:mlppyaz2ypciqsheyw3yjgt4","communities":["f81","s1563","c1794","g65861","e7784","o448833"]},{"did":"did:plc:mlpqe2wejxpt2m3or5yrier5","communities":["f218","s119","c562","g15516","e52576","o2231"]},{"did":"did:plc:mlpqghci6yqdlyvziwtu7ylc","communities":["f22","s284","c442","g20511","e2676240","o2398268"]},{"did":"did:plc:mlpqvmjk4ym3scshqjciqsdf","communities":["f10825","s3512","c3373","g5609","e3830","o2638"]},{"did":"did:plc:mlpred6ffqseeqrimmdvt6ix","communities":["f2586","s1321","c11895","g13893","e1173","o3204"]},{"did":"did:plc:mlprfbiq25knvh2azl3kdds7","communities":["f53","s10","c471","g1748197","e1145062","o354426"]},{"did":"did:plc:mlprji7basypvfehkrhb2mi4","communities":["f19","s18","c2012","g8065","e66873","o807594"]},{"did":"did:plc:mlprulp5hqoec46o3d64n2gd","communities":["f218","s119","c562","g9833","e1475876","o3182033"]},{"did":"did:plc:mlpsg4xppgbaa3fhl2zsxf3c","communities":["f81","s22707","c3750","g3069707","e3382759","o314498"]},{"did":"did:plc:mlpski243didhgjbpepbrsmt","communities":["f1017","s36199","c9324","g24572","e30989","o15414"]},{"did":"did:plc:mlpsovxjlxdh5fafnbjwpwl2","communities":["f2593","s506","c182","g4355","e66289","o5357"]},{"did":"did:plc:mlpsyepgipyx3yol5hesk5am","communities":["f560","s20","c1351","g12481","e1764632","o1368188"]},{"did":"did:plc:mlptd6kjmzvxmy7dk3lzz4in","communities":["f133","s1303","c3112","g278","e1604316","o796236"]},{"did":"did:plc:mlptoz6x6vejesezmrc5ffpc","communities":["f92","s97","c29383","g15557","e13561","o4804"]},{"did":"did:plc:mlpua5udjud3c6xpsrhevwr5","communities":["f390","s236","c35067","g15565","e5994","o365048"]},{"did":"did:plc:mlpuduur663l5eyve3pfsrqw","communities":["f21","s177","c95","g71916","e32012","o2469000"]},{"did":"did:plc:mlpvjycwkhub5dcllvtnfytp","communities":["f22","s622","c61","g249","e101931","o2474321"]},{"did":"did:plc:mlpw4sbwuhhdxedrrjivgnvg","communities":["f53","s506","c5852","g45094","e2717104","o350339"]},{"did":"did:plc:mlpw53uu4mtx2jtbo72dntcu","communities":["f29","s203","c4449","g61814","e1890971","o1663823"]},{"did":"did:plc:mlpwox2htlssaz6k6h2jyqgn","communities":["f133","s885","c174","g27019","e12563","o20649"]},{"did":"did:plc:mlpxeknpm2oblcneuzbc5kal","communities":["f22","s284","c442","g105","e14803","o20377"]},{"did":"did:plc:mlpxjxnj7g2nbsd6fyqik3a2","communities":["f81","s167","c10","g1608","e15979","o10830"]},{"did":"did:plc:mlpxnx5jy4dbpw36nndef2lw","communities":["f22","s9350","c689","g8397","e10612","o9308"]},{"did":"did:plc:mlpzizqr26lxkl7k2aluak7w","communities":["f560","s20","c1351","g219","e1307150","o809649"]},{"did":"did:plc:mlpzpmjrb42mazxfcyt7d7c7","communities":["f112","s677","c286","g108","e84610","o696563"]},{"did":"did:plc:mlpztqck7nup36arn6bswdmi","communities":["f17577","s103243","c26486","g1645850","e2599508","o1371238"]}]}