{"graphVersion":3,"nodes":[{"did":"did:plc:mti2h5m4ttcietm2ue4tdh56","communities":["f19","s461","c374","g1345","e16351","o3498"]},{"did":"did:plc:mti3yqx7xzeepy5z4rh4zxod","communities":["f261","s15","c36","g45309","e25125","o159964"]},{"did":"did:plc:mti4b664xwzuj3oqxsm7nixw","communities":["f261","s15","c36","g2018","e3566","o2267"]},{"did":"did:plc:mti4jwsfafmaspsszpn7i7tg","communities":["f70","s390","c5272","g12336","e686195","o539116"]},{"did":"did:plc:mti4n7ebybaxg53aeq7geein","communities":["f21","s177","c165934","g121370","e31717","o365031"]},{"did":"did:plc:mti4sbvsj4nk46ajxxf2t3ny","communities":["f21","s177","c95","g6871","e44044","o12077"]},{"did":"did:plc:mti4sjotc2nrja5ikmwxdkm5","communities":["f19","s7103","c2277","g106099","e87446","o505"]},{"did":"did:plc:mti4yhmsowa3omallsyu5jcs","communities":["f53","s167","c16842","g1222797","e108425","o1397272"]},{"did":"did:plc:mti5xes2kzkby6zdfiduq4fw","communities":["f112","s677","c86681","g12906","e2199","o63363"]},{"did":"did:plc:mti6rwn5rq32yrjbleqhfncn","communities":["f53","s64","c376","g507","e6193","o31281"]},{"did":"did:plc:mti6vr5pgukvdizalkwyu3nv","communities":["f2671","s622","c61","g249","e5305","o87806"]},{"did":"did:plc:mti6wbajm6ipvaqjmqvlm747","communities":["f501","s468","c47","g2596233","e1829032","o2014974"]},{"did":"did:plc:mti75phh2u56dyvfaprr45fy","communities":["f2671","s6576","c31934","g15876","e63401","o2843907"]},{"did":"did:plc:mti7uyobzwqbbg66subj6goc","communities":["f248","s203","c1305728","g1172811","e205858","o159317"]},{"did":"did:plc:mtiaqf3dxvdmmldzsx4nwbfl","communities":["f133","s4373","c23933","g2494","e4176","o2543"]},{"did":"did:plc:mtibdjv5g4pbyaw55cboqgo4","communities":["f395","s225","c317","g342","e3216073","o510604"]},{"did":"did:plc:mtibpr36f3d42ps7w32ruq56","communities":["f21","s11400","c165934","g272849","e2404748","o2805315"]},{"did":"did:plc:mtibqditaukja2zofoiu7wmg","communities":["f21","s177","c95","g218","e26481","o1543631"]},{"did":"did:plc:mticyxs6digbzy2cvijrze5b","communities":["f39","s2353","c471","g2582444","e943009","o2719592"]},{"did":"did:plc:mtidqwkukrasafb2c3aum2ni","communities":["f70","s767","c2960","g54","e3263883","o1815099"]},{"did":"did:plc:mtie4n6kc5qegp7dkpc3clkx","communities":["f395","s225","c254","g1054","e3332324","o2527030"]},{"did":"did:plc:mtiefvjr4gmej7uu3lh3jwfd","communities":["f29","s2289","c16035","g13752","e1128807","o1602404"]},{"did":"did:plc:mtierzw4jjli3tlqbuvcb4yi","communities":["f248","s203","c419","g369","e962","o6483"]},{"did":"did:plc:mtif6cxy67s6z5zdjeu6laud","communities":["f245","s97","c595","g2023","e2909475","o1016284"]},{"did":"did:plc:mtif7wlv6uc2nlbif6ss7tay","communities":["f398","s103","c195","g10041","e2441638","o2236950"]},{"did":"did:plc:mtifg5shiqd6gk323vadsz2l","communities":["f91","s137","c89","e2352035","o2890787"]},{"did":"did:plc:mtig2fhktkakmejsnollvw6l","communities":["f53","s2758","c2661","g368","e28069","o550437"]},{"did":"did:plc:mtigemyo6rklnv4mwgchi53c","communities":["f21","s177","c95","g6871","e235","o1638"]},{"did":"did:plc:mtigx2ekeppwqroezp7c3ysm","communities":["f19","s78","c331","g89","e5147","o2118"]},{"did":"did:plc:mtihdtrbdnl3x2afurktr4kq","communities":["f29","s5147","c1305728","g46985","e82664","o2951566"]},{"did":"did:plc:mtihgvbzbd4x3ep34mi3dybw","communities":["f29","s2627","c34095","g22222","e6274","o6233"]},{"did":"did:plc:mtihssxkfpf3mcfes5ouuxoc","communities":["f81","s1698","c5684","g3185756","e1444178","o830704"]},{"did":"did:plc:mtiibted6ubjgkebavuqyr4g","communities":["f218","s119","c8","g9936","e3448","o5688"]},{"did":"did:plc:mtijplafoum7jlpzdtzjqfsk","communities":["f14745","s17121","c28787","g12395","e139409","o1522"]},{"did":"did:plc:mtijqqprgjs6d2byzso26f6k","communities":["f218","s119","c8","g4733","e4420","o1346"]},{"did":"did:plc:mtimd4eo7kpyfir2uwnihxoa","communities":["f92","s97","c595","g335","e1660638","o1209972"]},{"did":"did:plc:mtimghpqh5wdojgnhc2bzqqj","communities":["f19","s18","c86","g488","e2812041","o1936974"]},{"did":"did:plc:mtimuh527sma6jtpmk5b7doe","communities":["f13","s3616","c186368","g3180716","e1658251","o114808"]},{"did":"did:plc:mtinzprm47gmkoldlryj7e4v","communities":["f21","s177","c604","g15841","e725101","o3073934"]},{"did":"did:plc:mtioa4j4epjpgrgdona4uwpo","communities":["f133","s6681","c10023","g2647","e40522","o51422"]},{"did":"did:plc:mtioidj6qmeezbhyaotqcygv","communities":["f81","s42130","c3429","g24074","e3233012","o2264404"]},{"did":"did:plc:mtipixffjqnfi36f2ix5b7uy","communities":["f285","s1698","c5684","g4094","e1614406","o3012958"]},{"did":"did:plc:mtis7kbugi6ygcqmb4w76zmt","communities":["f398","s103","c469","g1852","e3334293","o1137058"]},{"did":"did:plc:mtisuc7fw7hoaogixu5io2ij","communities":["f2671","s622","c61","g249","e4454","o5786"]},{"did":"did:plc:mtisuzapy576agbhqe2cvvok","communities":["f119","s810","c7771","g928","e198","o2896190"]},{"did":"did:plc:mtit3gkqpilceitz4tahnipj","communities":["f554","s1236","c812","g887","e60592","o969034"]},{"did":"did:plc:mtitnefw3dwsrm5zmq2szc5v","communities":["f21","s177","c2613","g15222","e2086819","o2853001"]},{"did":"did:plc:mtitt5tvjacg2pxret266nsn","communities":["f248","s203","c419","g369","e70366","o185866"]},{"did":"did:plc:mtitz5tlpi6amq5mp27zsxff","communities":["f19","s7103","c2277","g14016","e65379","o124378"]},{"did":"did:plc:mtiu2ljcmxvvc2aiopeworaz","communities":["f53","s1","c3697","g13143","e144610","o1018071"]},{"did":"did:plc:mtiunkkmv2ungsxiezxd4ayp","communities":["f29","s291","c419","g1645850","e387005","o446813"]},{"did":"did:plc:mtiuobmhrashkmuxfrfuayi5","communities":["f119","s810","c3596","g2329","e4367","o8411"]},{"did":"did:plc:mtiuxqqqdvtvlzpxq3ajmdfz","communities":["f245","s97","c595","g473","e36926","o2103453"]},{"did":"did:plc:mtivvhiseinvjtlwjnkjkiao","communities":["f21","s203","c20969","g352947","e2613821","o2322107"]},{"did":"did:plc:mtiwdfwvub33f6xi6yaerqxd","communities":["f21","s468","c44351","g2598215","e788135","o2849039"]},{"did":"did:plc:mtiwhnwi2wb326gpzvwbc7fi","communities":["f53","s1","c3697","g17170","e5624","o124468"]},{"did":"did:plc:mtixdcz5hk73oeqxy2wxuwhc","communities":["f19","s18","c11354","g6306","e2905730","o183069"]},{"did":"did:plc:mtiyt5etqbb2fy4gy74av67x","communities":["f81","s1144","c1427","g125","e2320","o2892331"]},{"did":"did:plc:mtiz2i6igascaerz2nihhauy","communities":["f398","s13012","c4640","g1576664","e2520641","o2446910"]}]}