{"graphVersion":3,"nodes":[{"did":"did:plc:uo523rxq4kewzoto3b6f4ci7","communities":["f53","s1476","c580","g10350","e5696","o3152956"]},{"did":"did:plc:uo526e527acwtrupogih2vjl","communities":["f21","s177","c16035","g20149","e67433","o3127033"]},{"did":"did:plc:uo533roqf25vwy7pjyqtssn7","communities":["f496","s759","c0","g73","e6389","o2884"]},{"did":"did:plc:uo53q552an4tekstlbvhqv5v","communities":["f53","s64","c376","g507","e15487","o31281"]},{"did":"did:plc:uo54ucdea57upr7a7qaxzi45","communities":["f19","s18","c374","g1345","e722574","o2795381"]},{"did":"did:plc:uo55ppxlkuzvql4zmah7fe6e","communities":["f2593","s1395","c327","g21915","e25254","o4275"]},{"did":"did:plc:uo55sgovhcdvsl6x66phe2n4","communities":["f21","s99","c4449","g10751","e83276","o123438"]},{"did":"did:plc:uo55vf25na37gbzrhls36xcd","communities":["f81","s10","c9568","g1465210","e1781361","o1386189"]},{"did":"did:plc:uo56hcnnwifftqr5ybu53sue","communities":["f21","s177","c95","g872","e4065","o9791"]},{"did":"did:plc:uo56zfdn6t2aok6yuwgtbdng","communities":["f21","s291","c328087","g302518","e1483224","o3084146"]},{"did":"did:plc:uo57as7zykvkrkfprqcc6ltv","communities":["f21","s71509","c55092","e1593506","o1052763"]},{"did":"did:plc:uo57etugxffvmuquzkjevmlo","communities":["f19","s18","c286","g940942","e2946863","o2856848"]},{"did":"did:plc:uo5bnosfdlgefbrpf3jrzby7","communities":["f53","s82935","c45963","g28957","e16932","o2565541"]},{"did":"did:plc:uo5bri5tgndebqcyk56t57cp","communities":["f5423","s11079","c18691","g14636","e8703","o3453"]},{"did":"did:plc:uo5dkc6jdcord6r6hzuqh4cw","communities":["f133","s476","c3112","g31915","e747147","o2204672"]},{"did":"did:plc:uo5dlfia2beqdwevlfeuztp2","communities":["f81","s1563","c86197","g14050","e2498880","o2462488"]},{"did":"did:plc:uo5dpdejxnzemp2vehrvcuse","communities":["f112","s677","c286","g108","e5828","o4559"]},{"did":"did:plc:uo5e7samfgmdjtntemmw2qfi","communities":["f21","s18727","c2613","g15222","e137263","o149214"]},{"did":"did:plc:uo5efcwpigvovt4zge24cot6","communities":["f22","s5792","c1983","g6451","e1793370","o281591"]},{"did":"did:plc:uo5eygwwvmhdzyqzb7csndya","communities":["f22","s193235","c14942","g1055406","e1583205","o1521170"]},{"did":"did:plc:uo5fimhnmcvxffgnv7joybmf","communities":["f21","s203","c8856","g13893","e107084","o2034805"]},{"did":"did:plc:uo5fxduxtvbh2l4hhxntldoe","communities":["f390","s47","c1867","g119","o1645741"]},{"did":"did:plc:uo5jaf7uzlberahzpb7eizvc","communities":["f70","s390","c148977","g189443","e1944352","o2514410"]},{"did":"did:plc:uo5kimcozd75wqrhfnsblcz2","communities":["f390","s15699","c35067","g15504","e12934","o9432"]},{"did":"did:plc:uo5km2hqabzsv65tukwt5tuj","communities":["f248","s203","c419","g369","e70366","o185866"]},{"did":"did:plc:uo5lttrts77jv7npxaoerpku","communities":["f112","s677","c286","g108","e55793","o12846"]},{"did":"did:plc:uo5mubg4pqvyciugnyw3re2x","communities":["f53","s256657","c37614","g11914","e26410","o3872"]},{"did":"did:plc:uo5mubp3r77bhhpdaks2ep4h","communities":["f248","s203","c419","g369","e962","o1348386"]},{"did":"did:plc:uo5n4w6dd6dditsrearztfsm","communities":["f218","s18607","c12902","g9936","e5213","o7265"]},{"did":"did:plc:uo5n6le6sc7mvlu4mretj5ml","communities":["f19","s78","c331","g89","e5147","o18447"]},{"did":"did:plc:uo5nffj6u764pynxhfhtiw63","communities":["f21","s99","c4449","g10751","e83276","o1737126"]},{"did":"did:plc:uo5o573g3fykj56wld3p4e5w","communities":["f81","s6589","c14630","g676","e186875","o6719"]},{"did":"did:plc:uo5oiw4xw6vt2vomcmzk7g2c","communities":["f91","s137","c89","g157","e491","o459074"]},{"did":"did:plc:uo5pjhbqb2gyljxvulr5v4vs","communities":["f1464","s1533","c8856","g1624","e210515","o324823"]},{"did":"did:plc:uo5ppafxv4s32qu53kq3goo7","communities":["f22","s284","c294","g8397","e10612","o2885756"]},{"did":"did:plc:uo5pv2ei5bgpe4vltkm4oksq","communities":["f21","s177","c95","g1220664","e1880158","o1845732"]},{"did":"did:plc:uo5qah7f7cl7eeubqlz3sg6j","communities":["f81","s1144","c1427","g125","e2320","o1033328"]},{"did":"did:plc:uo5qjyy7c3us7vmgfqxaubpq","communities":["f22","s284","c442","g13588","e121712","o725665"]},{"did":"did:plc:uo5qtfeawqhlettdjbm5i4x5","communities":["f247","s868","c722","g8597","e1040734","o426949"]},{"did":"did:plc:uo5rpboe2iwzkq6gbfwg2tqo","communities":["f21","s66170","c86609","g20032","e3326553","o1980239"]},{"did":"did:plc:uo5s4jmm67u546qhk5ecr554","communities":["f501","s468","c47","g148","e755","o1052986"]},{"did":"did:plc:uo5su4p2w56hizjsgobisbbb","communities":["f1464","s1533","c8856","g1624","e210515","o324823"]},{"did":"did:plc:uo5sxt3q3re7rlcamluawhqj","communities":["f29","s468","c61","g2982839","e450140","o709451"]},{"did":"did:plc:uo5syliul5hvlc54hfi5nj3q","communities":["f1287","s594","c566","g2056","e6774","o15286"]},{"did":"did:plc:uo5t4e35o5m7ihcgt6ugk4yt","communities":["f81","s3095","c1408","g4203","e13551","o2851114"]},{"did":"did:plc:uo5tupn4tbuwr44mt2rr6a4h","communities":["f261","s15","c36","g126434","e4441","o58977"]},{"did":"did:plc:uo5unbref5ya77tmwkkld3wu","communities":["f1464","s1533","c8856","g1624","e210515","o286356"]},{"did":"did:plc:uo5va2dt2nofbkc3uptjfauv","communities":["f133","s885","c26473","g11568","e873042","o49934"]},{"did":"did:plc:uo5vetlarqlrssm4f5j253mn","communities":["f398","s1","c350","g780675","e347378","o491383"]},{"did":"did:plc:uo5vr6qizm2wn4ti5lm6a2gb","communities":["f19886","s17529","c22602","g30434","e4638","o2283"]},{"did":"did:plc:uo5wgv4u2ood5zfvbhdyhg7t","communities":["f81","s242","c2626","g17048","e7357","o1601192"]},{"did":"did:plc:uo5x5x5scbvaubf7tjao3uoo","communities":["f81","s439","c2814","g6306","e3004897","o2095504"]},{"did":"did:plc:uo5x7qbigyssbcz75shizikg","communities":["f187","s1850","c1316","g898","e5152","o10476"]},{"did":"did:plc:uo5xrvktj47amd7co5pnrpub","communities":["f1464","s1533","c8856","g20198","e3179574","o431678"]},{"did":"did:plc:uo5yatp7ptynuzhdrxmjcqqk","communities":["f21","s177","c95","g872","e4065","o9791"]},{"did":"did:plc:uo5ykxczee2stb5jrlhxom4o","communities":["f2671","s622","c61","g249","e5305","o2129725"]},{"did":"did:plc:uo5yru4ans364sbdevwghaou","communities":["f70","s802","c277","g151","e5308","o678741"]},{"did":"did:plc:uo5zfxq6bfidonhl6itlu3r5","communities":["f645","s2302","c1377","g17595","e11276","o40968"]}]}